LICENSE
README.md
setup.py
keeper_secrets_manager_cli/__init__.py
keeper_secrets_manager_cli/__main__.py
keeper_secrets_manager_cli/common.py
keeper_secrets_manager_cli/config.py
keeper_secrets_manager_cli/exception.py
keeper_secrets_manager_cli/exec.py
keeper_secrets_manager_cli/export.py
keeper_secrets_manager_cli/folder.py
keeper_secrets_manager_cli/init.py
keeper_secrets_manager_cli/interpolate.py
keeper_secrets_manager_cli/profile.py
keeper_secrets_manager_cli/secret.py
keeper_secrets_manager_cli/sync.py
keeper_secrets_manager_cli/table.py
keeper_secrets_manager_cli.egg-info/PKG-INFO
keeper_secrets_manager_cli.egg-info/SOURCES.txt
keeper_secrets_manager_cli.egg-info/dependency_links.txt
keeper_secrets_manager_cli.egg-info/entry_points.txt
keeper_secrets_manager_cli.egg-info/not-zip-safe
keeper_secrets_manager_cli.egg-info/requires.txt
keeper_secrets_manager_cli.egg-info/top_level.txt