Metadata-Version: 2.4
Name: keeper-secrets-manager-cli
Version: 1.2.0
Summary: Command line tool for Keeper Secrets Manager
Home-page: https://github.com/Keeper-Security/secrets-manager
Author: Keeper Security
Author-email: sm@keepersecurity.com
License: MIT
Project-URL: Bug Tracker, https://github.com/Keeper-Security/secrets-manager/issues
Project-URL: Documentation, https://app.gitbook.com/@keeper-security/s/secrets-manager/secrets-manager/secrets-manager-command-line-interface
Project-URL: Source Code, https://github.com/Keeper-Security/secrets-manager
Keywords: Keeper Password Secrets Manager SDK CLI
Classifier: Development Status :: 5 - Production/Stable
Classifier: Intended Audience :: Developers
Classifier: License :: OSI Approved :: MIT License
Classifier: Operating System :: OS Independent
Classifier: Programming Language :: Python
Classifier: Programming Language :: Python :: 3
Classifier: Programming Language :: Python :: 3.7
Classifier: Programming Language :: Python :: 3.8
Classifier: Programming Language :: Python :: 3.9
Classifier: Programming Language :: Python :: 3.10
Classifier: Programming Language :: Python :: 3.11
Classifier: Programming Language :: Python :: 3.12
Classifier: Programming Language :: Python :: 3.13
Classifier: Topic :: Security
Requires-Python: >=3.7
License-File: LICENSE
Requires-Dist: pip>=24.3.1
Requires-Dist: keeper-secrets-manager-core>=17.0.0
Requires-Dist: keeper-secrets-manager-helper>=1.0.6
Requires-Dist: keeper-secrets-manager-storage>=1.0.2
Requires-Dist: prompt-toolkit~=2.0
Requires-Dist: jsonpath-rw-ext
Requires-Dist: colorama
Requires-Dist: importlib_metadata
Requires-Dist: click
Requires-Dist: click_help_colors
Requires-Dist: click-repl
Requires-Dist: pyyaml
Requires-Dist: update-checker
Requires-Dist: psutil
Requires-Dist: boto3
Dynamic: author
Dynamic: author-email
Dynamic: classifier
Dynamic: description
Dynamic: description-content-type
Dynamic: home-page
Dynamic: keywords
Dynamic: license
Dynamic: license-file
Dynamic: project-url
Dynamic: requires-dist
Dynamic: requires-python
Dynamic: summary
